{
  "config_dir": "/Users/svenhockers/Desktop/project/topology-and-robustness-in-DNNs/config/final/nested_spheres",
  "dataset_name": "VECTOR",
  "elapsed_s": 10105.827738046646,
  "metric_path": "auto",
  "minimize": false,
  "model_name": "MLP",
  "n_initial": 5,
  "n_trials": 15,
  "runs": [
    {
      "best": {
        "duration_s": 69.2304892539978,
        "error": null,
        "metric_value": 0.5606209588510473,
        "notes": "suggest=gp_ei",
        "objective_value": 0.5606209588510473,
        "params": {
          "detector.topo_cov_shrinkage": 1.7918311875568857e-06,
          "detector.topo_percentile": 81.79654833266557,
          "graph.k": 95,
          "graph.topo_k": 6,
          "graph.topo_min_persistence": 3.742755539154038e-07,
          "graph.topo_pca_dim": 43,
          "graph.topo_preprocess": "none"
        },
        "run_dir": "/Users/svenhockers/Desktop/project/topology-and-robustness-in-DNNs/out/nested_spheres/base_torus_one_hole_e_0.1/runs/trials/trial_000011",
        "status": "success",
        "trial_id": 11
      },
      "config_path": "/Users/svenhockers/Desktop/project/topology-and-robustness-in-DNNs/config/final/nested_spheres/base_torus_one_hole_e_0.1.yaml",
      "config_relpath": "base_torus_one_hole_e_0.1.yaml",
      "duration_s": 969.3806037902832,
      "error": null,
      "status": "success",
      "study_dir": "/Users/svenhockers/Desktop/project/topology-and-robustness-in-DNNs/out/nested_spheres/base_torus_one_hole_e_0.1"
    },
    {
      "best": {
        "duration_s": 47.15070295333862,
        "error": null,
        "metric_value": 0.5310062651834804,
        "notes": "suggest=gp_ei",
        "objective_value": 0.5310062651834804,
        "params": {
          "detector.topo_cov_shrinkage": 0.04804016486697805,
          "detector.topo_percentile": 86.7800508118794,
          "graph.k": 53,
          "graph.topo_k": 69,
          "graph.topo_min_persistence": 5.99921284889588e-08,
          "graph.topo_pca_dim": 12,
          "graph.topo_preprocess": "pca"
        },
        "run_dir": "/Users/svenhockers/Desktop/project/topology-and-robustness-in-DNNs/out/nested_spheres/base_torus_one_hole_e_0.2/runs/trials/trial_000013",
        "status": "success",
        "trial_id": 13
      },
      "config_path": "/Users/svenhockers/Desktop/project/topology-and-robustness-in-DNNs/config/final/nested_spheres/base_torus_one_hole_e_0.2.yaml",
      "config_relpath": "base_torus_one_hole_e_0.2.yaml",
      "duration_s": 838.2430973052979,
      "error": null,
      "status": "success",
      "study_dir": "/Users/svenhockers/Desktop/project/topology-and-robustness-in-DNNs/out/nested_spheres/base_torus_one_hole_e_0.2"
    },
    {
      "best": {
        "duration_s": 66.0837037563324,
        "error": null,
        "metric_value": 0.5606209588510473,
        "notes": "suggest=gp_ei",
        "objective_value": 0.5606209588510473,
        "params": {
          "detector.topo_cov_shrinkage": 1.7918311875568857e-06,
          "detector.topo_percentile": 81.79654833266557,
          "graph.k": 95,
          "graph.topo_k": 6,
          "graph.topo_min_persistence": 3.742755539154038e-07,
          "graph.topo_pca_dim": 43,
          "graph.topo_preprocess": "none"
        },
        "run_dir": "/Users/svenhockers/Desktop/project/topology-and-robustness-in-DNNs/out/nested_spheres/base_torus_one_hole_e_0.3_copy/runs/trials/trial_000011",
        "status": "success",
        "trial_id": 11
      },
      "config_path": "/Users/svenhockers/Desktop/project/topology-and-robustness-in-DNNs/config/final/nested_spheres/base_torus_one_hole_e_0.3 copy.yaml",
      "config_relpath": "base_torus_one_hole_e_0.3 copy.yaml",
      "duration_s": 937.2929179668427,
      "error": null,
      "status": "success",
      "study_dir": "/Users/svenhockers/Desktop/project/topology-and-robustness-in-DNNs/out/nested_spheres/base_torus_one_hole_e_0.3_copy"
    },
    {
      "best": {
        "duration_s": 47.46691584587097,
        "error": null,
        "metric_value": 0.6521855725395549,
        "notes": "suggest=gp_ei",
        "objective_value": 0.6521855725395549,
        "params": {
          "detector.topo_cov_shrinkage": 0.00017374860901299836,
          "detector.topo_percentile": 87.01878043950703,
          "graph.k": 63,
          "graph.topo_k": 60,
          "graph.topo_min_persistence": 0.0006259896510445709,
          "graph.topo_pca_dim": 8,
          "graph.topo_preprocess": "none"
        },
        "run_dir": "/Users/svenhockers/Desktop/project/topology-and-robustness-in-DNNs/out/nested_spheres/baseline/base_torus_one_hole_e_0.1/runs/trials/trial_000009",
        "status": "success",
        "trial_id": 9
      },
      "config_path": "/Users/svenhockers/Desktop/project/topology-and-robustness-in-DNNs/config/final/nested_spheres/baseline/base_torus_one_hole_e_0.1.yaml",
      "config_relpath": "baseline/base_torus_one_hole_e_0.1.yaml",
      "duration_s": 734.5575618743896,
      "error": null,
      "status": "success",
      "study_dir": "/Users/svenhockers/Desktop/project/topology-and-robustness-in-DNNs/out/nested_spheres/baseline/base_torus_one_hole_e_0.1"
    },
    {
      "best": {
        "duration_s": 16.869510889053345,
        "error": null,
        "metric_value": 0.6938584153774027,
        "notes": "suggest=random",
        "objective_value": 0.6938584153774027,
        "params": {
          "detector.topo_cov_shrinkage": 0.01203642655937434,
          "detector.topo_percentile": 90.08565609478795,
          "graph.k": 8,
          "graph.topo_k": 14,
          "graph.topo_min_persistence": 0.0003488865093860712,
          "graph.topo_pca_dim": 12,
          "graph.topo_preprocess": "none"
        },
        "run_dir": "/Users/svenhockers/Desktop/project/topology-and-robustness-in-DNNs/out/nested_spheres/baseline/base_torus_one_hole_e_0.2/runs/trials/trial_000003",
        "status": "success",
        "trial_id": 3
      },
      "config_path": "/Users/svenhockers/Desktop/project/topology-and-robustness-in-DNNs/config/final/nested_spheres/baseline/base_torus_one_hole_e_0.2.yaml",
      "config_relpath": "baseline/base_torus_one_hole_e_0.2.yaml",
      "duration_s": 635.0157766342163,
      "error": null,
      "status": "success",
      "study_dir": "/Users/svenhockers/Desktop/project/topology-and-robustness-in-DNNs/out/nested_spheres/baseline/base_torus_one_hole_e_0.2"
    },
    {
      "best": {
        "duration_s": 48.32760190963745,
        "error": null,
        "metric_value": 0.6521855725395549,
        "notes": "suggest=gp_ei",
        "objective_value": 0.6521855725395549,
        "params": {
          "detector.topo_cov_shrinkage": 0.00017374860901299836,
          "detector.topo_percentile": 87.01878043950703,
          "graph.k": 63,
          "graph.topo_k": 60,
          "graph.topo_min_persistence": 0.0006259896510445709,
          "graph.topo_pca_dim": 8,
          "graph.topo_preprocess": "none"
        },
        "run_dir": "/Users/svenhockers/Desktop/project/topology-and-robustness-in-DNNs/out/nested_spheres/baseline/base_torus_one_hole_e_0.3_copy/runs/trials/trial_000009",
        "status": "success",
        "trial_id": 9
      },
      "config_path": "/Users/svenhockers/Desktop/project/topology-and-robustness-in-DNNs/config/final/nested_spheres/baseline/base_torus_one_hole_e_0.3 copy.yaml",
      "config_relpath": "baseline/base_torus_one_hole_e_0.3 copy.yaml",
      "duration_s": 747.6718220710754,
      "error": null,
      "status": "success",
      "study_dir": "/Users/svenhockers/Desktop/project/topology-and-robustness-in-DNNs/out/nested_spheres/baseline/base_torus_one_hole_e_0.3_copy"
    },
    {
      "best": {
        "duration_s": 114.97545218467712,
        "error": null,
        "metric_value": 0.7242312008978675,
        "notes": "suggest=gp_ei",
        "objective_value": 0.7242312008978675,
        "params": {
          "detector.topo_cov_shrinkage": 0.06443044768328501,
          "detector.topo_percentile": 96.33239928996382,
          "graph.k": 117,
          "graph.topo_k": 40,
          "graph.topo_min_persistence": 0.00016183336523927633,
          "graph.topo_pca_dim": 8,
          "graph.topo_preprocess": "none"
        },
        "run_dir": "/Users/svenhockers/Desktop/project/topology-and-robustness-in-DNNs/out/nested_spheres/OOD/ood_baseline_noise/runs/trials/trial_000015",
        "status": "success",
        "trial_id": 15
      },
      "config_path": "/Users/svenhockers/Desktop/project/topology-and-robustness-in-DNNs/config/final/nested_spheres/OOD/ood_baseline_noise.yaml",
      "config_relpath": "OOD/ood_baseline_noise.yaml",
      "duration_s": 1238.0047187805176,
      "error": null,
      "status": "success",
      "study_dir": "/Users/svenhockers/Desktop/project/topology-and-robustness-in-DNNs/out/nested_spheres/OOD/ood_baseline_noise"
    },
    {
      "best": {
        "duration_s": 100.0911169052124,
        "error": null,
        "metric_value": 0.9540067340067341,
        "notes": "suggest=gp_ei",
        "objective_value": 0.9540067340067341,
        "params": {
          "detector.topo_cov_shrinkage": 1.2336826080138366e-05,
          "detector.topo_percentile": 86.24393427770846,
          "graph.k": 103,
          "graph.topo_k": 65,
          "graph.topo_min_persistence": 3.5661371578886715e-05,
          "graph.topo_pca_dim": 38,
          "graph.topo_preprocess": "pca"
        },
        "run_dir": "/Users/svenhockers/Desktop/project/topology-and-robustness-in-DNNs/out/nested_spheres/OOD/ood_baseline_shift/runs/trials/trial_000011",
        "status": "success",
        "trial_id": 11
      },
      "config_path": "/Users/svenhockers/Desktop/project/topology-and-robustness-in-DNNs/config/final/nested_spheres/OOD/ood_baseline_shift.yaml",
      "config_relpath": "OOD/ood_baseline_shift.yaml",
      "duration_s": 1235.729877948761,
      "error": null,
      "status": "success",
      "study_dir": "/Users/svenhockers/Desktop/project/topology-and-robustness-in-DNNs/out/nested_spheres/OOD/ood_baseline_shift"
    },
    {
      "best": {
        "duration_s": 87.65577721595764,
        "error": null,
        "metric_value": 0.617250280583614,
        "notes": "suggest=gp_ei",
        "objective_value": 0.617250280583614,
        "params": {
          "detector.topo_cov_shrinkage": 3.82854506837102e-06,
          "detector.topo_percentile": 86.35018387317248,
          "graph.k": 85,
          "graph.topo_k": 10,
          "graph.topo_min_persistence": 0.0003956881796670063,
          "graph.topo_pca_dim": 44,
          "graph.topo_preprocess": "pca"
        },
        "run_dir": "/Users/svenhockers/Desktop/project/topology-and-robustness-in-DNNs/out/nested_spheres/OOD/ood_baseline_shuffle/runs/trials/trial_000012",
        "status": "success",
        "trial_id": 12
      },
      "config_path": "/Users/svenhockers/Desktop/project/topology-and-robustness-in-DNNs/config/final/nested_spheres/OOD/ood_baseline_shuffle.yaml",
      "config_relpath": "OOD/ood_baseline_shuffle.yaml",
      "duration_s": 1295.5968599319458,
      "error": null,
      "status": "success",
      "study_dir": "/Users/svenhockers/Desktop/project/topology-and-robustness-in-DNNs/out/nested_spheres/OOD/ood_baseline_shuffle"
    },
    {
      "best": {
        "duration_s": 4.947221994400024,
        "error": null,
        "metric_value": 0.5606209588510473,
        "notes": "suggest=gp_ei",
        "objective_value": 0.5606209588510473,
        "params": {
          "detector.topo_cov_shrinkage": 1.7918311875568857e-06,
          "detector.topo_percentile": 81.79654833266557,
          "graph.k": 95,
          "graph.topo_k": 6,
          "graph.topo_min_persistence": 3.742755539154038e-07,
          "graph.topo_pca_dim": 43,
          "graph.topo_preprocess": "none"
        },
        "run_dir": "/Users/svenhockers/Desktop/project/topology-and-robustness-in-DNNs/out/nested_spheres/topology_only/base_torus_one_hole_e_0.1/runs/trials/trial_000011",
        "status": "success",
        "trial_id": 11
      },
      "config_path": "/Users/svenhockers/Desktop/project/topology-and-robustness-in-DNNs/config/final/nested_spheres/topology_only/base_torus_one_hole_e_0.1.yaml",
      "config_relpath": "topology_only/base_torus_one_hole_e_0.1.yaml",
      "duration_s": 132.6820878982544,
      "error": null,
      "status": "success",
      "study_dir": "/Users/svenhockers/Desktop/project/topology-and-robustness-in-DNNs/out/nested_spheres/topology_only/base_torus_one_hole_e_0.1"
    },
    {
      "best": {
        "duration_s": 10.214090824127197,
        "error": null,
        "metric_value": 0.5310062651834804,
        "notes": "suggest=gp_ei",
        "objective_value": 0.5310062651834804,
        "params": {
          "detector.topo_cov_shrinkage": 0.04804016486697805,
          "detector.topo_percentile": 86.7800508118794,
          "graph.k": 53,
          "graph.topo_k": 69,
          "graph.topo_min_persistence": 5.99921284889588e-08,
          "graph.topo_pca_dim": 12,
          "graph.topo_preprocess": "pca"
        },
        "run_dir": "/Users/svenhockers/Desktop/project/topology-and-robustness-in-DNNs/out/nested_spheres/topology_only/base_torus_one_hole_e_0.2/runs/trials/trial_000013",
        "status": "success",
        "trial_id": 13
      },
      "config_path": "/Users/svenhockers/Desktop/project/topology-and-robustness-in-DNNs/config/final/nested_spheres/topology_only/base_torus_one_hole_e_0.2.yaml",
      "config_relpath": "topology_only/base_torus_one_hole_e_0.2.yaml",
      "duration_s": 172.05557584762573,
      "error": null,
      "status": "success",
      "study_dir": "/Users/svenhockers/Desktop/project/topology-and-robustness-in-DNNs/out/nested_spheres/topology_only/base_torus_one_hole_e_0.2"
    },
    {
      "best": {
        "duration_s": 4.864035129547119,
        "error": null,
        "metric_value": 0.5606209588510473,
        "notes": "suggest=gp_ei",
        "objective_value": 0.5606209588510473,
        "params": {
          "detector.topo_cov_shrinkage": 1.7918311875568857e-06,
          "detector.topo_percentile": 81.79654833266557,
          "graph.k": 95,
          "graph.topo_k": 6,
          "graph.topo_min_persistence": 3.742755539154038e-07,
          "graph.topo_pca_dim": 43,
          "graph.topo_preprocess": "none"
        },
        "run_dir": "/Users/svenhockers/Desktop/project/topology-and-robustness-in-DNNs/out/nested_spheres/topology_only/base_torus_one_hole_e_0.3_copy/runs/trials/trial_000011",
        "status": "success",
        "trial_id": 11
      },
      "config_path": "/Users/svenhockers/Desktop/project/topology-and-robustness-in-DNNs/config/final/nested_spheres/topology_only/base_torus_one_hole_e_0.3 copy.yaml",
      "config_relpath": "topology_only/base_torus_one_hole_e_0.3 copy.yaml",
      "duration_s": 132.32010698318481,
      "error": null,
      "status": "success",
      "study_dir": "/Users/svenhockers/Desktop/project/topology-and-robustness-in-DNNs/out/nested_spheres/topology_only/base_torus_one_hole_e_0.3_copy"
    }
  ],
  "seed": 30,
  "timestamp_unix_s": 1768600563.758523
}